{
  "402e2977_three_tree_1": {
    "wav": "{data_root}\\tensorflow-speech-recognition\\train\\402e2977\\402e2977_three_tree_1.wav",
    "length": 2.0,
    "spk_id": "402e2977"
  },
  "cd68e997_three_tree_3": {
    "wav": "{data_root}\\tensorflow-speech-recognition\\train\\cd68e997\\cd68e997_three_tree_3.wav",
    "length": 2.0,
    "spk_id": "cd68e997"
  },
  "4845bb10_three_tree_1": {
    "wav": "{data_root}\\tensorflow-speech-recognition\\train\\4845bb10\\4845bb10_three_tree_1.wav",
    "length": 2.0,
    "spk_id": "4845bb10"
  },
  "529eda42_three_tree_1": {
    "wav": "{data_root}\\tensorflow-speech-recognition\\train\\529eda42\\529eda42_three_tree_1.wav",
    "length": 2.0,
    "spk_id": "529eda42"
  },
  "1887fe04_three_tree_2": {
    "wav": "{data_root}\\tensorflow-speech-recognition\\train\\1887fe04\\1887fe04_three_tree_2.wav",
    "length": 2.0,
    "spk_id": "1887fe04"
  },
  "016e2c6d_three_tree_0": {
    "wav": "{data_root}\\tensorflow-speech-recognition\\train\\016e2c6d\\016e2c6d_three_tree_0.wav",
    "length": 2.0,
    "spk_id": "016e2c6d"
  },
  "483e2a6f_three_tree_0": {
    "wav": "{data_root}\\tensorflow-speech-recognition\\train\\483e2a6f\\483e2a6f_three_tree_0.wav",
    "length": 2.0,
    "spk_id": "483e2a6f"
  },
  "98447c43_three_tree_1": {
    "wav": "{data_root}\\tensorflow-speech-recognition\\train\\98447c43\\98447c43_three_tree_1.wav",
    "length": 2.0,
    "spk_id": "98447c43"
  },
  "3cdecb0b_three_tree_3": {
    "wav": "{data_root}\\tensorflow-speech-recognition\\train\\3cdecb0b\\3cdecb0b_three_tree_3.wav",
    "length": 2.0,
    "spk_id": "3cdecb0b"
  },
  "98447c43_three_tree_0": {
    "wav": "{data_root}\\tensorflow-speech-recognition\\train\\98447c43\\98447c43_three_tree_0.wav",
    "length": 2.0,
    "spk_id": "98447c43"
  },
  "2df590cd_three_tree_2": {
    "wav": "{data_root}\\tensorflow-speech-recognition\\train\\2df590cd\\2df590cd_three_tree_2.wav",
    "length": 1.76475,
    "spk_id": "2df590cd"
  },
  "e2008f39_three_tree_2": {
    "wav": "{data_root}\\tensorflow-speech-recognition\\train\\e2008f39\\e2008f39_three_tree_2.wav",
    "length": 2.0,
    "spk_id": "e2008f39"
  },
  "8781f4c1_three_tree_3": {
    "wav": "{data_root}\\tensorflow-speech-recognition\\train\\8781f4c1\\8781f4c1_three_tree_3.wav",
    "length": 2.0,
    "spk_id": "8781f4c1"
  },
  "a24582a0_three_tree_3": {
    "wav": "{data_root}\\tensorflow-speech-recognition\\train\\a24582a0\\a24582a0_three_tree_3.wav",
    "length": 2.0,
    "spk_id": "a24582a0"
  },
  "863880b7_three_tree_0": {
    "wav": "{data_root}\\tensorflow-speech-recognition\\train\\863880b7\\863880b7_three_tree_0.wav",
    "length": 2.0,
    "spk_id": "863880b7"
  },
  "402e2977_three_tree_2": {
    "wav": "{data_root}\\tensorflow-speech-recognition\\train\\402e2977\\402e2977_three_tree_2.wav",
    "length": 2.0,
    "spk_id": "402e2977"
  },
  "b59fe16d_three_tree_2": {
    "wav": "{data_root}\\tensorflow-speech-recognition\\train\\b59fe16d\\b59fe16d_three_tree_2.wav",
    "length": 2.0,
    "spk_id": "b59fe16d"
  },
  "b19f7f5f_three_tree_2": {
    "wav": "{data_root}\\tensorflow-speech-recognition\\train\\b19f7f5f\\b19f7f5f_three_tree_2.wav",
    "length": 2.0,
    "spk_id": "b19f7f5f"
  },
  "1ed557b9_three_tree_2": {
    "wav": "{data_root}\\tensorflow-speech-recognition\\train\\1ed557b9\\1ed557b9_three_tree_2.wav",
    "length": 2.0,
    "spk_id": "1ed557b9"
  },
  "65ec06e5_three_tree_2": {
    "wav": "{data_root}\\tensorflow-speech-recognition\\train\\65ec06e5\\65ec06e5_three_tree_2.wav",
    "length": 2.0,
    "spk_id": "65ec06e5"
  },
  "1887fe04_three_tree_1": {
    "wav": "{data_root}\\tensorflow-speech-recognition\\train\\1887fe04\\1887fe04_three_tree_1.wav",
    "length": 2.0,
    "spk_id": "1887fe04"
  },
  "1887fe04_three_tree_0": {
    "wav": "{data_root}\\tensorflow-speech-recognition\\train\\1887fe04\\1887fe04_three_tree_0.wav",
    "length": 2.0,
    "spk_id": "1887fe04"
  },
  "7be9f58a_three_tree_2": {
    "wav": "{data_root}\\tensorflow-speech-recognition\\train\\7be9f58a\\7be9f58a_three_tree_2.wav",
    "length": 2.0,
    "spk_id": "7be9f58a"
  },
  "9a7c1f83_three_tree_0": {
    "wav": "{data_root}\\tensorflow-speech-recognition\\train\\9a7c1f83\\9a7c1f83_three_tree_0.wav",
    "length": 2.0,
    "spk_id": "9a7c1f83"
  },
  "c86d4fd4_three_tree_0": {
    "wav": "{data_root}\\tensorflow-speech-recognition\\train\\c86d4fd4\\c86d4fd4_three_tree_0.wav",
    "length": 2.0,
    "spk_id": "c86d4fd4"
  },
  "6c6aa323_three_tree_2": {
    "wav": "{data_root}\\tensorflow-speech-recognition\\train\\6c6aa323\\6c6aa323_three_tree_2.wav",
    "length": 2.0,
    "spk_id": "6c6aa323"
  },
  "9a43b64b_three_tree_3": {
    "wav": "{data_root}\\tensorflow-speech-recognition\\train\\9a43b64b\\9a43b64b_three_tree_3.wav",
    "length": 2.0,
    "spk_id": "9a43b64b"
  },
  "80c45ed6_three_tree_2": {
    "wav": "{data_root}\\tensorflow-speech-recognition\\train\\80c45ed6\\80c45ed6_three_tree_2.wav",
    "length": 2.0,
    "spk_id": "80c45ed6"
  },
  "9712cce0_three_tree_1": {
    "wav": "{data_root}\\tensorflow-speech-recognition\\train\\9712cce0\\9712cce0_three_tree_1.wav",
    "length": 1.896,
    "spk_id": "9712cce0"
  },
  "019fa366_three_tree_3": {
    "wav": "{data_root}\\tensorflow-speech-recognition\\train\\019fa366\\019fa366_three_tree_3.wav",
    "length": 2.0,
    "spk_id": "019fa366"
  },
  "7be9f58a_three_tree_3": {
    "wav": "{data_root}\\tensorflow-speech-recognition\\train\\7be9f58a\\7be9f58a_three_tree_3.wav",
    "length": 2.0,
    "spk_id": "7be9f58a"
  },
  "7bf801d1_three_tree_3": {
    "wav": "{data_root}\\tensorflow-speech-recognition\\train\\7bf801d1\\7bf801d1_three_tree_3.wav",
    "length": 2.0,
    "spk_id": "7bf801d1"
  },
  "d9ae8983_three_tree_1": {
    "wav": "{data_root}\\tensorflow-speech-recognition\\train\\d9ae8983\\d9ae8983_three_tree_1.wav",
    "length": 2.0,
    "spk_id": "d9ae8983"
  },
  "7be9f58a_three_tree_0": {
    "wav": "{data_root}\\tensorflow-speech-recognition\\train\\7be9f58a\\7be9f58a_three_tree_0.wav",
    "length": 2.0,
    "spk_id": "7be9f58a"
  },
  "e0ff1e9c_three_tree_1": {
    "wav": "{data_root}\\tensorflow-speech-recognition\\train\\e0ff1e9c\\e0ff1e9c_three_tree_1.wav",
    "length": 2.0,
    "spk_id": "e0ff1e9c"
  },
  "e0ff1e9c_three_tree_2": {
    "wav": "{data_root}\\tensorflow-speech-recognition\\train\\e0ff1e9c\\e0ff1e9c_three_tree_2.wav",
    "length": 2.0,
    "spk_id": "e0ff1e9c"
  },
  "7be9f58a_three_tree_1": {
    "wav": "{data_root}\\tensorflow-speech-recognition\\train\\7be9f58a\\7be9f58a_three_tree_1.wav",
    "length": 2.0,
    "spk_id": "7be9f58a"
  },
  "571c044e_three_tree_0": {
    "wav": "{data_root}\\tensorflow-speech-recognition\\train\\571c044e\\571c044e_three_tree_0.wav",
    "length": 2.0,
    "spk_id": "571c044e"
  },
  "016e2c6d_three_tree_1": {
    "wav": "{data_root}\\tensorflow-speech-recognition\\train\\016e2c6d\\016e2c6d_three_tree_1.wav",
    "length": 2.0,
    "spk_id": "016e2c6d"
  },
  "9f7079fe_three_tree_0": {
    "wav": "{data_root}\\tensorflow-speech-recognition\\train\\9f7079fe\\9f7079fe_three_tree_0.wav",
    "length": 2.0,
    "spk_id": "9f7079fe"
  },
  "e0a7c5a0_three_tree_0": {
    "wav": "{data_root}\\tensorflow-speech-recognition\\train\\e0a7c5a0\\e0a7c5a0_three_tree_0.wav",
    "length": 2.0,
    "spk_id": "e0a7c5a0"
  },
  "7bf801d1_three_tree_0": {
    "wav": "{data_root}\\tensorflow-speech-recognition\\train\\7bf801d1\\7bf801d1_three_tree_0.wav",
    "length": 2.0,
    "spk_id": "7bf801d1"
  },
  "9efe5140_three_tree_1": {
    "wav": "{data_root}\\tensorflow-speech-recognition\\train\\9efe5140\\9efe5140_three_tree_1.wav",
    "length": 1.981375,
    "spk_id": "9efe5140"
  },
  "e77d88fc_three_tree_2": {
    "wav": "{data_root}\\tensorflow-speech-recognition\\train\\e77d88fc\\e77d88fc_three_tree_2.wav",
    "length": 2.0,
    "spk_id": "e77d88fc"
  },
  "8781f4c1_three_tree_0": {
    "wav": "{data_root}\\tensorflow-speech-recognition\\train\\8781f4c1\\8781f4c1_three_tree_0.wav",
    "length": 2.0,
    "spk_id": "8781f4c1"
  },
  "24632875_three_tree_1": {
    "wav": "{data_root}\\tensorflow-speech-recognition\\train\\24632875\\24632875_three_tree_1.wav",
    "length": 2.0,
    "spk_id": "24632875"
  },
  "b63fea9e_three_tree_1": {
    "wav": "{data_root}\\tensorflow-speech-recognition\\train\\b63fea9e\\b63fea9e_three_tree_1.wav",
    "length": 2.0,
    "spk_id": "b63fea9e"
  },
  "e0ff1e9c_three_tree_3": {
    "wav": "{data_root}\\tensorflow-speech-recognition\\train\\e0ff1e9c\\e0ff1e9c_three_tree_3.wav",
    "length": 2.0,
    "spk_id": "e0ff1e9c"
  },
  "a24582a0_three_tree_1": {
    "wav": "{data_root}\\tensorflow-speech-recognition\\train\\a24582a0\\a24582a0_three_tree_1.wav",
    "length": 2.0,
    "spk_id": "a24582a0"
  },
  "cd68e997_three_tree_0": {
    "wav": "{data_root}\\tensorflow-speech-recognition\\train\\cd68e997\\cd68e997_three_tree_0.wav",
    "length": 2.0,
    "spk_id": "cd68e997"
  },
  "1ed557b9_three_tree_1": {
    "wav": "{data_root}\\tensorflow-speech-recognition\\train\\1ed557b9\\1ed557b9_three_tree_1.wav",
    "length": 2.0,
    "spk_id": "1ed557b9"
  },
  "483e2a6f_three_tree_1": {
    "wav": "{data_root}\\tensorflow-speech-recognition\\train\\483e2a6f\\483e2a6f_three_tree_1.wav",
    "length": 2.0,
    "spk_id": "483e2a6f"
  },
  "65ec06e5_three_tree_1": {
    "wav": "{data_root}\\tensorflow-speech-recognition\\train\\65ec06e5\\65ec06e5_three_tree_1.wav",
    "length": 2.0,
    "spk_id": "65ec06e5"
  },
  "7e6bd776_three_tree_0": {
    "wav": "{data_root}\\tensorflow-speech-recognition\\train\\7e6bd776\\7e6bd776_three_tree_0.wav",
    "length": 2.0,
    "spk_id": "7e6bd776"
  },
  "36de13e1_three_tree_2": {
    "wav": "{data_root}\\tensorflow-speech-recognition\\train\\36de13e1\\36de13e1_three_tree_2.wav",
    "length": 2.0,
    "spk_id": "36de13e1"
  },
  "a8f45bdc_three_tree_1": {
    "wav": "{data_root}\\tensorflow-speech-recognition\\train\\a8f45bdc\\a8f45bdc_three_tree_1.wav",
    "length": 2.0,
    "spk_id": "a8f45bdc"
  },
  "019fa366_three_tree_2": {
    "wav": "{data_root}\\tensorflow-speech-recognition\\train\\019fa366\\019fa366_three_tree_2.wav",
    "length": 2.0,
    "spk_id": "019fa366"
  },
  "377e916b_three_tree_0": {
    "wav": "{data_root}\\tensorflow-speech-recognition\\train\\377e916b\\377e916b_three_tree_0.wav",
    "length": 1.8106875,
    "spk_id": "377e916b"
  },
  "9efe5140_three_tree_0": {
    "wav": "{data_root}\\tensorflow-speech-recognition\\train\\9efe5140\\9efe5140_three_tree_0.wav",
    "length": 1.981375,
    "spk_id": "9efe5140"
  },
  "d9ae8983_three_tree_0": {
    "wav": "{data_root}\\tensorflow-speech-recognition\\train\\d9ae8983\\d9ae8983_three_tree_0.wav",
    "length": 2.0,
    "spk_id": "d9ae8983"
  },
  "9a7c1f83_three_tree_3": {
    "wav": "{data_root}\\tensorflow-speech-recognition\\train\\9a7c1f83\\9a7c1f83_three_tree_3.wav",
    "length": 2.0,
    "spk_id": "9a7c1f83"
  },
  "24632875_three_tree_2": {
    "wav": "{data_root}\\tensorflow-speech-recognition\\train\\24632875\\24632875_three_tree_2.wav",
    "length": 2.0,
    "spk_id": "24632875"
  },
  "22aa3665_three_tree_0": {
    "wav": "{data_root}\\tensorflow-speech-recognition\\train\\22aa3665\\22aa3665_three_tree_0.wav",
    "length": 1.5360625,
    "spk_id": "22aa3665"
  },
  "377e916b_three_tree_3": {
    "wav": "{data_root}\\tensorflow-speech-recognition\\train\\377e916b\\377e916b_three_tree_3.wav",
    "length": 1.8106875,
    "spk_id": "377e916b"
  },
  "80b8eab4_three_tree_1": {
    "wav": "{data_root}\\tensorflow-speech-recognition\\train\\80b8eab4\\80b8eab4_three_tree_1.wav",
    "length": 2.0,
    "spk_id": "80b8eab4"
  },
  "529eda42_three_tree_0": {
    "wav": "{data_root}\\tensorflow-speech-recognition\\train\\529eda42\\529eda42_three_tree_0.wav",
    "length": 2.0,
    "spk_id": "529eda42"
  },
  "a8f45bdc_three_tree_2": {
    "wav": "{data_root}\\tensorflow-speech-recognition\\train\\a8f45bdc\\a8f45bdc_three_tree_2.wav",
    "length": 2.0,
    "spk_id": "a8f45bdc"
  },
  "b19f7f5f_three_tree_3": {
    "wav": "{data_root}\\tensorflow-speech-recognition\\train\\b19f7f5f\\b19f7f5f_three_tree_3.wav",
    "length": 2.0,
    "spk_id": "b19f7f5f"
  },
  "80b8eab4_three_tree_0": {
    "wav": "{data_root}\\tensorflow-speech-recognition\\train\\80b8eab4\\80b8eab4_three_tree_0.wav",
    "length": 2.0,
    "spk_id": "80b8eab4"
  },
  "24632875_three_tree_3": {
    "wav": "{data_root}\\tensorflow-speech-recognition\\train\\24632875\\24632875_three_tree_3.wav",
    "length": 2.0,
    "spk_id": "24632875"
  },
  "863880b7_three_tree_1": {
    "wav": "{data_root}\\tensorflow-speech-recognition\\train\\863880b7\\863880b7_three_tree_1.wav",
    "length": 2.0,
    "spk_id": "863880b7"
  },
  "36de13e1_three_tree_0": {
    "wav": "{data_root}\\tensorflow-speech-recognition\\train\\36de13e1\\36de13e1_three_tree_0.wav",
    "length": 2.0,
    "spk_id": "36de13e1"
  },
  "e2008f39_three_tree_3": {
    "wav": "{data_root}\\tensorflow-speech-recognition\\train\\e2008f39\\e2008f39_three_tree_3.wav",
    "length": 2.0,
    "spk_id": "e2008f39"
  },
  "b06c19b0_three_tree_0": {
    "wav": "{data_root}\\tensorflow-speech-recognition\\train\\b06c19b0\\b06c19b0_three_tree_0.wav",
    "length": 2.0,
    "spk_id": "b06c19b0"
  },
  "8781f4c1_three_tree_1": {
    "wav": "{data_root}\\tensorflow-speech-recognition\\train\\8781f4c1\\8781f4c1_three_tree_1.wav",
    "length": 2.0,
    "spk_id": "8781f4c1"
  },
  "24632875_three_tree_0": {
    "wav": "{data_root}\\tensorflow-speech-recognition\\train\\24632875\\24632875_three_tree_0.wav",
    "length": 2.0,
    "spk_id": "24632875"
  },
  "22aa3665_three_tree_3": {
    "wav": "{data_root}\\tensorflow-speech-recognition\\train\\22aa3665\\22aa3665_three_tree_3.wav",
    "length": 1.5360625,
    "spk_id": "22aa3665"
  },
  "09ddc105_three_tree_0": {
    "wav": "{data_root}\\tensorflow-speech-recognition\\train\\09ddc105\\09ddc105_three_tree_0.wav",
    "length": 1.981375,
    "spk_id": "09ddc105"
  },
  "1626bc5a_three_tree_0": {
    "wav": "{data_root}\\tensorflow-speech-recognition\\train\\1626bc5a\\1626bc5a_three_tree_0.wav",
    "length": 2.0,
    "spk_id": "1626bc5a"
  },
  "402e2977_three_tree_3": {
    "wav": "{data_root}\\tensorflow-speech-recognition\\train\\402e2977\\402e2977_three_tree_3.wav",
    "length": 2.0,
    "spk_id": "402e2977"
  },
  "e77d88fc_three_tree_3": {
    "wav": "{data_root}\\tensorflow-speech-recognition\\train\\e77d88fc\\e77d88fc_three_tree_3.wav",
    "length": 2.0,
    "spk_id": "e77d88fc"
  },
  "e2008f39_three_tree_0": {
    "wav": "{data_root}\\tensorflow-speech-recognition\\train\\e2008f39\\e2008f39_three_tree_0.wav",
    "length": 2.0,
    "spk_id": "e2008f39"
  },
  "402e2977_three_tree_0": {
    "wav": "{data_root}\\tensorflow-speech-recognition\\train\\402e2977\\402e2977_three_tree_0.wav",
    "length": 2.0,
    "spk_id": "402e2977"
  },
  "9f7079fe_three_tree_2": {
    "wav": "{data_root}\\tensorflow-speech-recognition\\train\\9f7079fe\\9f7079fe_three_tree_2.wav",
    "length": 2.0,
    "spk_id": "9f7079fe"
  },
  "17f0e206_three_tree_1": {
    "wav": "{data_root}\\tensorflow-speech-recognition\\train\\17f0e206\\17f0e206_three_tree_1.wav",
    "length": 2.0,
    "spk_id": "17f0e206"
  },
  "e2008f39_three_tree_1": {
    "wav": "{data_root}\\tensorflow-speech-recognition\\train\\e2008f39\\e2008f39_three_tree_1.wav",
    "length": 2.0,
    "spk_id": "e2008f39"
  },
  "3cdecb0b_three_tree_1": {
    "wav": "{data_root}\\tensorflow-speech-recognition\\train\\3cdecb0b\\3cdecb0b_three_tree_1.wav",
    "length": 2.0,
    "spk_id": "3cdecb0b"
  },
  "6c6aa323_three_tree_0": {
    "wav": "{data_root}\\tensorflow-speech-recognition\\train\\6c6aa323\\6c6aa323_three_tree_0.wav",
    "length": 2.0,
    "spk_id": "6c6aa323"
  },
  "9f7079fe_three_tree_3": {
    "wav": "{data_root}\\tensorflow-speech-recognition\\train\\9f7079fe\\9f7079fe_three_tree_3.wav",
    "length": 2.0,
    "spk_id": "9f7079fe"
  },
  "7e6bd776_three_tree_2": {
    "wav": "{data_root}\\tensorflow-speech-recognition\\train\\7e6bd776\\7e6bd776_three_tree_2.wav",
    "length": 2.0,
    "spk_id": "7e6bd776"
  },
  "9a43b64b_three_tree_1": {
    "wav": "{data_root}\\tensorflow-speech-recognition\\train\\9a43b64b\\9a43b64b_three_tree_1.wav",
    "length": 2.0,
    "spk_id": "9a43b64b"
  },
  "019fa366_three_tree_1": {
    "wav": "{data_root}\\tensorflow-speech-recognition\\train\\019fa366\\019fa366_three_tree_1.wav",
    "length": 2.0,
    "spk_id": "019fa366"
  },
  "9f7079fe_three_tree_1": {
    "wav": "{data_root}\\tensorflow-speech-recognition\\train\\9f7079fe\\9f7079fe_three_tree_1.wav",
    "length": 2.0,
    "spk_id": "9f7079fe"
  },
  "e77d88fc_three_tree_1": {
    "wav": "{data_root}\\tensorflow-speech-recognition\\train\\e77d88fc\\e77d88fc_three_tree_1.wav",
    "length": 2.0,
    "spk_id": "e77d88fc"
  },
  "016e2c6d_three_tree_3": {
    "wav": "{data_root}\\tensorflow-speech-recognition\\train\\016e2c6d\\016e2c6d_three_tree_3.wav",
    "length": 2.0,
    "spk_id": "016e2c6d"
  },
  "17f0e206_three_tree_2": {
    "wav": "{data_root}\\tensorflow-speech-recognition\\train\\17f0e206\\17f0e206_three_tree_2.wav",
    "length": 2.0,
    "spk_id": "17f0e206"
  },
  "17f0e206_three_tree_3": {
    "wav": "{data_root}\\tensorflow-speech-recognition\\train\\17f0e206\\17f0e206_three_tree_3.wav",
    "length": 2.0,
    "spk_id": "17f0e206"
  },
  "e0a7c5a0_three_tree_2": {
    "wav": "{data_root}\\tensorflow-speech-recognition\\train\\e0a7c5a0\\e0a7c5a0_three_tree_2.wav",
    "length": 2.0,
    "spk_id": "e0a7c5a0"
  },
  "9a43b64b_three_tree_0": {
    "wav": "{data_root}\\tensorflow-speech-recognition\\train\\9a43b64b\\9a43b64b_three_tree_0.wav",
    "length": 2.0,
    "spk_id": "9a43b64b"
  },
  "529eda42_three_tree_2": {
    "wav": "{data_root}\\tensorflow-speech-recognition\\train\\529eda42\\529eda42_three_tree_2.wav",
    "length": 2.0,
    "spk_id": "529eda42"
  },
  "9a43b64b_three_tree_2": {
    "wav": "{data_root}\\tensorflow-speech-recognition\\train\\9a43b64b\\9a43b64b_three_tree_2.wav",
    "length": 2.0,
    "spk_id": "9a43b64b"
  },
  "bcdaa7a9_three_tree_0": {
    "wav": "{data_root}\\tensorflow-speech-recognition\\train\\bcdaa7a9\\bcdaa7a9_three_tree_0.wav",
    "length": 2.0,
    "spk_id": "bcdaa7a9"
  },
  "3cdecb0b_three_tree_2": {
    "wav": "{data_root}\\tensorflow-speech-recognition\\train\\3cdecb0b\\3cdecb0b_three_tree_2.wav",
    "length": 2.0,
    "spk_id": "3cdecb0b"
  },
  "98447c43_three_tree_2": {
    "wav": "{data_root}\\tensorflow-speech-recognition\\train\\98447c43\\98447c43_three_tree_2.wav",
    "length": 2.0,
    "spk_id": "98447c43"
  },
  "377e916b_three_tree_2": {
    "wav": "{data_root}\\tensorflow-speech-recognition\\train\\377e916b\\377e916b_three_tree_2.wav",
    "length": 1.8106875,
    "spk_id": "377e916b"
  },
  "6c6aa323_three_tree_1": {
    "wav": "{data_root}\\tensorflow-speech-recognition\\train\\6c6aa323\\6c6aa323_three_tree_1.wav",
    "length": 2.0,
    "spk_id": "6c6aa323"
  },
  "2df590cd_three_tree_3": {
    "wav": "{data_root}\\tensorflow-speech-recognition\\train\\2df590cd\\2df590cd_three_tree_3.wav",
    "length": 1.76475,
    "spk_id": "2df590cd"
  },
  "a8f45bdc_three_tree_3": {
    "wav": "{data_root}\\tensorflow-speech-recognition\\train\\a8f45bdc\\a8f45bdc_three_tree_3.wav",
    "length": 2.0,
    "spk_id": "a8f45bdc"
  },
  "a24582a0_three_tree_0": {
    "wav": "{data_root}\\tensorflow-speech-recognition\\train\\a24582a0\\a24582a0_three_tree_0.wav",
    "length": 2.0,
    "spk_id": "a24582a0"
  },
  "1887fe04_three_tree_3": {
    "wav": "{data_root}\\tensorflow-speech-recognition\\train\\1887fe04\\1887fe04_three_tree_3.wav",
    "length": 2.0,
    "spk_id": "1887fe04"
  },
  "483e2a6f_three_tree_2": {
    "wav": "{data_root}\\tensorflow-speech-recognition\\train\\483e2a6f\\483e2a6f_three_tree_2.wav",
    "length": 2.0,
    "spk_id": "483e2a6f"
  },
  "2df590cd_three_tree_1": {
    "wav": "{data_root}\\tensorflow-speech-recognition\\train\\2df590cd\\2df590cd_three_tree_1.wav",
    "length": 1.76475,
    "spk_id": "2df590cd"
  },
  "571c044e_three_tree_1": {
    "wav": "{data_root}\\tensorflow-speech-recognition\\train\\571c044e\\571c044e_three_tree_1.wav",
    "length": 2.0,
    "spk_id": "571c044e"
  },
  "17f0e206_three_tree_0": {
    "wav": "{data_root}\\tensorflow-speech-recognition\\train\\17f0e206\\17f0e206_three_tree_0.wav",
    "length": 2.0,
    "spk_id": "17f0e206"
  },
  "7bf801d1_three_tree_2": {
    "wav": "{data_root}\\tensorflow-speech-recognition\\train\\7bf801d1\\7bf801d1_three_tree_2.wav",
    "length": 2.0,
    "spk_id": "7bf801d1"
  },
  "e0a7c5a0_three_tree_3": {
    "wav": "{data_root}\\tensorflow-speech-recognition\\train\\e0a7c5a0\\e0a7c5a0_three_tree_3.wav",
    "length": 2.0,
    "spk_id": "e0a7c5a0"
  },
  "626e323f_three_tree_0": {
    "wav": "{data_root}\\tensorflow-speech-recognition\\train\\626e323f\\626e323f_three_tree_0.wav",
    "length": 1.7183125,
    "spk_id": "626e323f"
  },
  "b06c19b0_three_tree_3": {
    "wav": "{data_root}\\tensorflow-speech-recognition\\train\\b06c19b0\\b06c19b0_three_tree_3.wav",
    "length": 2.0,
    "spk_id": "b06c19b0"
  },
  "09ddc105_three_tree_3": {
    "wav": "{data_root}\\tensorflow-speech-recognition\\train\\09ddc105\\09ddc105_three_tree_3.wav",
    "length": 1.981375,
    "spk_id": "09ddc105"
  },
  "d33df435_three_tree_0": {
    "wav": "{data_root}\\tensorflow-speech-recognition\\train\\d33df435\\d33df435_three_tree_0.wav",
    "length": 2.0,
    "spk_id": "d33df435"
  },
  "bcdaa7a9_three_tree_3": {
    "wav": "{data_root}\\tensorflow-speech-recognition\\train\\bcdaa7a9\\bcdaa7a9_three_tree_3.wav",
    "length": 2.0,
    "spk_id": "bcdaa7a9"
  },
  "6c6aa323_three_tree_3": {
    "wav": "{data_root}\\tensorflow-speech-recognition\\train\\6c6aa323\\6c6aa323_three_tree_3.wav",
    "length": 2.0,
    "spk_id": "6c6aa323"
  },
  "b63fea9e_three_tree_2": {
    "wav": "{data_root}\\tensorflow-speech-recognition\\train\\b63fea9e\\b63fea9e_three_tree_2.wav",
    "length": 2.0,
    "spk_id": "b63fea9e"
  },
  "a8f45bdc_three_tree_0": {
    "wav": "{data_root}\\tensorflow-speech-recognition\\train\\a8f45bdc\\a8f45bdc_three_tree_0.wav",
    "length": 2.0,
    "spk_id": "a8f45bdc"
  },
  "c86d4fd4_three_tree_1": {
    "wav": "{data_root}\\tensorflow-speech-recognition\\train\\c86d4fd4\\c86d4fd4_three_tree_1.wav",
    "length": 2.0,
    "spk_id": "c86d4fd4"
  },
  "8781f4c1_three_tree_2": {
    "wav": "{data_root}\\tensorflow-speech-recognition\\train\\8781f4c1\\8781f4c1_three_tree_2.wav",
    "length": 2.0,
    "spk_id": "8781f4c1"
  },
  "c86d4fd4_three_tree_2": {
    "wav": "{data_root}\\tensorflow-speech-recognition\\train\\c86d4fd4\\c86d4fd4_three_tree_2.wav",
    "length": 2.0,
    "spk_id": "c86d4fd4"
  },
  "e0a7c5a0_three_tree_1": {
    "wav": "{data_root}\\tensorflow-speech-recognition\\train\\e0a7c5a0\\e0a7c5a0_three_tree_1.wav",
    "length": 2.0,
    "spk_id": "e0a7c5a0"
  },
  "98447c43_three_tree_3": {
    "wav": "{data_root}\\tensorflow-speech-recognition\\train\\98447c43\\98447c43_three_tree_3.wav",
    "length": 2.0,
    "spk_id": "98447c43"
  },
  "626e323f_three_tree_2": {
    "wav": "{data_root}\\tensorflow-speech-recognition\\train\\626e323f\\626e323f_three_tree_2.wav",
    "length": 1.7183125,
    "spk_id": "626e323f"
  },
  "b63fea9e_three_tree_0": {
    "wav": "{data_root}\\tensorflow-speech-recognition\\train\\b63fea9e\\b63fea9e_three_tree_0.wav",
    "length": 2.0,
    "spk_id": "b63fea9e"
  },
  "d9ae8983_three_tree_3": {
    "wav": "{data_root}\\tensorflow-speech-recognition\\train\\d9ae8983\\d9ae8983_three_tree_3.wav",
    "length": 2.0,
    "spk_id": "d9ae8983"
  },
  "016e2c6d_three_tree_2": {
    "wav": "{data_root}\\tensorflow-speech-recognition\\train\\016e2c6d\\016e2c6d_three_tree_2.wav",
    "length": 2.0,
    "spk_id": "016e2c6d"
  },
  "80c45ed6_three_tree_3": {
    "wav": "{data_root}\\tensorflow-speech-recognition\\train\\80c45ed6\\80c45ed6_three_tree_3.wav",
    "length": 2.0,
    "spk_id": "80c45ed6"
  },
  "3cdecb0b_three_tree_0": {
    "wav": "{data_root}\\tensorflow-speech-recognition\\train\\3cdecb0b\\3cdecb0b_three_tree_0.wav",
    "length": 2.0,
    "spk_id": "3cdecb0b"
  },
  "b59fe16d_three_tree_3": {
    "wav": "{data_root}\\tensorflow-speech-recognition\\train\\b59fe16d\\b59fe16d_three_tree_3.wav",
    "length": 2.0,
    "spk_id": "b59fe16d"
  },
  "d33df435_three_tree_2": {
    "wav": "{data_root}\\tensorflow-speech-recognition\\train\\d33df435\\d33df435_three_tree_2.wav",
    "length": 2.0,
    "spk_id": "d33df435"
  },
  "7e6bd776_three_tree_1": {
    "wav": "{data_root}\\tensorflow-speech-recognition\\train\\7e6bd776\\7e6bd776_three_tree_1.wav",
    "length": 2.0,
    "spk_id": "7e6bd776"
  },
  "4845bb10_three_tree_0": {
    "wav": "{data_root}\\tensorflow-speech-recognition\\train\\4845bb10\\4845bb10_three_tree_0.wav",
    "length": 2.0,
    "spk_id": "4845bb10"
  },
  "c86d4fd4_three_tree_3": {
    "wav": "{data_root}\\tensorflow-speech-recognition\\train\\c86d4fd4\\c86d4fd4_three_tree_3.wav",
    "length": 2.0,
    "spk_id": "c86d4fd4"
  },
  "9a7c1f83_three_tree_1": {
    "wav": "{data_root}\\tensorflow-speech-recognition\\train\\9a7c1f83\\9a7c1f83_three_tree_1.wav",
    "length": 2.0,
    "spk_id": "9a7c1f83"
  },
  "b59fe16d_three_tree_0": {
    "wav": "{data_root}\\tensorflow-speech-recognition\\train\\b59fe16d\\b59fe16d_three_tree_0.wav",
    "length": 2.0,
    "spk_id": "b59fe16d"
  },
  "a1a59b72_three_tree_1": {
    "wav": "{data_root}\\tensorflow-speech-recognition\\train\\a1a59b72\\a1a59b72_three_tree_1.wav",
    "length": 2.0,
    "spk_id": "a1a59b72"
  },
  "9efe5140_three_tree_2": {
    "wav": "{data_root}\\tensorflow-speech-recognition\\train\\9efe5140\\9efe5140_three_tree_2.wav",
    "length": 1.981375,
    "spk_id": "9efe5140"
  },
  "2df590cd_three_tree_0": {
    "wav": "{data_root}\\tensorflow-speech-recognition\\train\\2df590cd\\2df590cd_three_tree_0.wav",
    "length": 1.76475,
    "spk_id": "2df590cd"
  },
  "36de13e1_three_tree_1": {
    "wav": "{data_root}\\tensorflow-speech-recognition\\train\\36de13e1\\36de13e1_three_tree_1.wav",
    "length": 2.0,
    "spk_id": "36de13e1"
  },
  "cd68e997_three_tree_2": {
    "wav": "{data_root}\\tensorflow-speech-recognition\\train\\cd68e997\\cd68e997_three_tree_2.wav",
    "length": 2.0,
    "spk_id": "cd68e997"
  },
  "65ec06e5_three_tree_0": {
    "wav": "{data_root}\\tensorflow-speech-recognition\\train\\65ec06e5\\65ec06e5_three_tree_0.wav",
    "length": 2.0,
    "spk_id": "65ec06e5"
  },
  "483e2a6f_three_tree_3": {
    "wav": "{data_root}\\tensorflow-speech-recognition\\train\\483e2a6f\\483e2a6f_three_tree_3.wav",
    "length": 2.0,
    "spk_id": "483e2a6f"
  },
  "1626bc5a_three_tree_3": {
    "wav": "{data_root}\\tensorflow-speech-recognition\\train\\1626bc5a\\1626bc5a_three_tree_3.wav",
    "length": 2.0,
    "spk_id": "1626bc5a"
  },
  "e77d88fc_three_tree_0": {
    "wav": "{data_root}\\tensorflow-speech-recognition\\train\\e77d88fc\\e77d88fc_three_tree_0.wav",
    "length": 2.0,
    "spk_id": "e77d88fc"
  },
  "80c45ed6_three_tree_0": {
    "wav": "{data_root}\\tensorflow-speech-recognition\\train\\80c45ed6\\80c45ed6_three_tree_0.wav",
    "length": 2.0,
    "spk_id": "80c45ed6"
  },
  "9a7c1f83_three_tree_2": {
    "wav": "{data_root}\\tensorflow-speech-recognition\\train\\9a7c1f83\\9a7c1f83_three_tree_2.wav",
    "length": 2.0,
    "spk_id": "9a7c1f83"
  },
  "9712cce0_three_tree_0": {
    "wav": "{data_root}\\tensorflow-speech-recognition\\train\\9712cce0\\9712cce0_three_tree_0.wav",
    "length": 1.896,
    "spk_id": "9712cce0"
  },
  "bcdaa7a9_three_tree_1": {
    "wav": "{data_root}\\tensorflow-speech-recognition\\train\\bcdaa7a9\\bcdaa7a9_three_tree_1.wav",
    "length": 2.0,
    "spk_id": "bcdaa7a9"
  },
  "1ed557b9_three_tree_0": {
    "wav": "{data_root}\\tensorflow-speech-recognition\\train\\1ed557b9\\1ed557b9_three_tree_0.wav",
    "length": 2.0,
    "spk_id": "1ed557b9"
  },
  "863880b7_three_tree_2": {
    "wav": "{data_root}\\tensorflow-speech-recognition\\train\\863880b7\\863880b7_three_tree_2.wav",
    "length": 2.0,
    "spk_id": "863880b7"
  },
  "571c044e_three_tree_3": {
    "wav": "{data_root}\\tensorflow-speech-recognition\\train\\571c044e\\571c044e_three_tree_3.wav",
    "length": 2.0,
    "spk_id": "571c044e"
  },
  "22aa3665_three_tree_2": {
    "wav": "{data_root}\\tensorflow-speech-recognition\\train\\22aa3665\\22aa3665_three_tree_2.wav",
    "length": 1.5360625,
    "spk_id": "22aa3665"
  },
  "b19f7f5f_three_tree_1": {
    "wav": "{data_root}\\tensorflow-speech-recognition\\train\\b19f7f5f\\b19f7f5f_three_tree_1.wav",
    "length": 2.0,
    "spk_id": "b19f7f5f"
  }
}